dbbasic_forms/__init__.py
dbbasic_forms/admin.py
dbbasic_forms/forms.py
dbbasic_forms/api/__init__.py
dbbasic_forms/api/forms/__init__.py
dbbasic_forms/api/forms/create.py
dbbasic_forms/api/forms/delete.py
dbbasic_forms/api/forms/edit.py
dbbasic_forms/api/forms/list.py
dbbasic_forms/api/forms/responses.py
dbbasic_forms/templates/forms/editor.html
dbbasic_forms/templates/forms/list.html
dbbasic_forms/templates/forms/responses.html
dbbasic_forms-1.0.1.dist-info/licenses/LICENSE
dbbasic_forms-1.0.1.dist-info/METADATA
dbbasic_forms-1.0.1.dist-info/WHEEL
dbbasic_forms-1.0.1.dist-info/top_level.txt
dbbasic_forms-1.0.1.dist-info/RECORD
