Metadata-Version: 2.4
Name: dbbasic-forms
Version: 1.0.1
Summary: A git-friendly form builder using TSV storage
Author: AskRobots Contributors
License: MIT
Project-URL: Homepage, https://github.com/askrobots/dbbasic-forms
Project-URL: Documentation, https://github.com/askrobots/dbbasic-forms#readme
Project-URL: Repository, https://github.com/askrobots/dbbasic-forms
Project-URL: Issues, https://github.com/askrobots/dbbasic-forms/issues
Keywords: forms,tsv,git,form-builder,no-database,static-forms
Classifier: Development Status :: 4 - Beta
Classifier: Intended Audience :: Developers
Classifier: Topic :: Internet :: WWW/HTTP :: Dynamic Content
Classifier: Topic :: Software Development :: Libraries :: Python Modules
Classifier: License :: OSI Approved :: MIT License
Classifier: Programming Language :: Python :: 3
Classifier: Programming Language :: Python :: 3.8
Classifier: Programming Language :: Python :: 3.9
Classifier: Programming Language :: Python :: 3.10
Classifier: Programming Language :: Python :: 3.11
Classifier: Programming Language :: Python :: 3.12
Classifier: Operating System :: OS Independent
Requires-Python: >=3.8
License-File: LICENSE
Requires-Dist: dbbasic-tsv>=1.0.0
Provides-Extra: dev
Requires-Dist: pytest>=7.0; extra == "dev"
Requires-Dist: pytest-cov>=4.0; extra == "dev"
Requires-Dist: black>=22.0; extra == "dev"
Requires-Dist: isort>=5.0; extra == "dev"
Requires-Dist: flake8>=5.0; extra == "dev"
Dynamic: license-file
